helptext/__init__.py
helptext/version.py
helptext-1.0.0.dist-info/METADATA
helptext-1.0.0.dist-info/WHEEL
helptext-1.0.0.dist-info/licenses/LICENSE
helptext-1.0.0.dist-info/RECORD
