Metadata-Version: 2.1
Name: helptext
Version: 1.0.0
Summary: A documentation-generated argument parser.
Project-URL: homepage, https://gitlab.com/helptext/helptext
Project-URL: documentation, https://gitlab.com/helptext/helptext
Project-URL: repository, https://gitlab.com/helptext/helptext
Author-email: Rob Thralls <robert.thralls@pm.me>
Maintainer-email: Rob Thralls <robert.thralls@pm.me>
License: Copyright (C) 2024 by Rob Thralls <robert.thralls@pm.me>
License-File: LICENSE
Keywords: argument,cli,command-line,docstring,getopt,help,helptext,interface,option,parser,text
Classifier: Development Status :: 5 - Production/Stable
Classifier: Environment :: Console
Classifier: Intended Audience :: Developers
Classifier: Intended Audience :: Information Technology
Classifier: Intended Audience :: System Administrators
Classifier: License :: OSI Approved
Classifier: License :: OSI Approved :: BSD License
Classifier: License :: OSI Approved :: Zero-Clause BSD (0BSD)
Classifier: Natural Language :: English
Classifier: Operating System :: OS Independent
Classifier: Operating System :: POSIX
Classifier: Operating System :: Unix
Classifier: Programming Language :: Python
Classifier: Programming Language :: Python :: 3
Classifier: Programming Language :: Python :: 3 :: Only
Requires-Python: >=3
